{"window":{"start":"2021-04-03T01:51:00.000Z","end":"2021-04-03T01:52:00.000Z"},"country":"France","OPM":1,"Total_sales_vol":133.04999709129333,"rate_of_return":0.0}
{"window":{"start":"2021-03-29T05:41:00.000Z","end":"2021-03-29T05:42:00.000Z"},"country":"United Kingdom","OPM":10,"Total_sales_vol":672.2100008130074,"rate_of_return":0.0}
{"window":{"start":"2021-03-26T17:04:00.000Z","end":"2021-03-26T17:05:00.000Z"},"country":"United Kingdom","OPM":8,"Total_sales_vol":490.09999346733093,"rate_of_return":0.0}
{"window":{"start":"2021-03-27T12:24:00.000Z","end":"2021-03-27T12:25:00.000Z"},"country":"Switzerland","OPM":1,"Total_sales_vol":7.5,"rate_of_return":0.0}
{"window":{"start":"2021-03-27T23:11:00.000Z","end":"2021-03-27T23:12:00.000Z"},"country":"EIRE","OPM":1,"Total_sales_vol":63.11999988555908,"rate_of_return":0.0}
{"window":{"start":"2021-03-28T12:44:00.000Z","end":"2021-03-28T12:45:00.000Z"},"country":"United Kingdom","OPM":12,"Total_sales_vol":674.8900014162064,"rate_of_return":0.07692307692307693}
{"window":{"start":"2021-03-28T00:07:00.000Z","end":"2021-03-28T00:08:00.000Z"},"country":"United Kingdom","OPM":9,"Total_sales_vol":945.4400011897087,"rate_of_return":0.0}
{"window":{"start":"2021-04-02T15:40:00.000Z","end":"2021-04-02T15:41:00.000Z"},"country":"United Kingdom","OPM":5,"Total_sales_vol":226.27999758720398,"rate_of_return":0.0}
{"window":{"start":"2021-03-27T06:15:00.000Z","end":"2021-03-27T06:16:00.000Z"},"country":"France","OPM":1,"Total_sales_vol":18.239999771118164,"rate_of_return":0.0}
{"window":{"start":"2021-03-31T01:54:00.000Z","end":"2021-03-31T01:55:00.000Z"},"country":"United Kingdom","OPM":8,"Total_sales_vol":200.31999802589417,"rate_of_return":0.0}
{"window":{"start":"2021-03-29T22:52:00.000Z","end":"2021-03-29T22:53:00.000Z"},"country":"United Kingdom","OPM":8,"Total_sales_vol":509.06999561190605,"rate_of_return":0.0}
{"window":{"start":"2021-03-26T15:49:00.000Z","end":"2021-03-26T15:50:00.000Z"},"country":"Germany","OPM":1,"Total_sales_vol":18.260000348091125,"rate_of_return":0.0}
{"window":{"start":"2021-03-30T10:32:00.000Z","end":"2021-03-30T10:33:00.000Z"},"country":"United Kingdom","OPM":9,"Total_sales_vol":483.7700024843216,"rate_of_return":0.0}
{"window":{"start":"2021-03-26T12:16:00.000Z","end":"2021-03-26T12:17:00.000Z"},"country":"France","OPM":1,"Total_sales_vol":25.00000023841858,"rate_of_return":0.0}
{"window":{"start":"2021-04-02T17:11:00.000Z","end":"2021-04-02T17:12:00.000Z"},"country":"United Kingdom","OPM":12,"Total_sales_vol":367.1500004827976,"rate_of_return":0.24324324324324326}
{"window":{"start":"2021-03-26T02:20:00.000Z","end":"2021-03-26T02:21:00.000Z"},"country":"United Kingdom","OPM":11,"Total_sales_vol":1745.5400239825249,"rate_of_return":0.02857142857142857}
{"window":{"start":"2021-03-28T15:05:00.000Z","end":"2021-03-28T15:06:00.000Z"},"country":"Switzerland","OPM":1,"Total_sales_vol":28.55000114440918,"rate_of_return":0.0}
{"window":{"start":"2021-03-26T20:15:00.000Z","end":"2021-03-26T20:16:00.000Z"},"country":"United Kingdom","OPM":10,"Total_sales_vol":512.9399968385696,"rate_of_return":0.0}
{"window":{"start":"2021-03-29T16:36:00.000Z","end":"2021-03-29T16:37:00.000Z"},"country":"Israel","OPM":1,"Total_sales_vol":18.960000038146973,"rate_of_return":0.0}
{"window":{"start":"2021-04-02T09:06:00.000Z","end":"2021-04-02T09:07:00.000Z"},"country":"United Kingdom","OPM":10,"Total_sales_vol":574.3099927008152,"rate_of_return":0.0}
{"window":{"start":"2021-04-01T19:23:00.000Z","end":"2021-04-01T19:24:00.000Z"},"country":"EIRE","OPM":1,"Total_sales_vol":60.260000228881836,"rate_of_return":0.0}
{"window":{"start":"2021-03-26T23:43:00.000Z","end":"2021-03-26T23:44:00.000Z"},"country":"EIRE","OPM":1,"Total_sales_vol":83.05999612808228,"rate_of_return":0.0}
{"window":{"start":"2021-04-01T14:35:00.000Z","end":"2021-04-01T14:36:00.000Z"},"country":"United Kingdom","OPM":12,"Total_sales_vol":2147.3600029945374,"rate_of_return":0.08333333333333333}
{"window":{"start":"2021-03-30T06:54:00.000Z","end":"2021-03-30T06:55:00.000Z"},"country":"United Kingdom","OPM":11,"Total_sales_vol":723.6800020933151,"rate_of_return":0.0}
{"window":{"start":"2021-04-02T11:17:00.000Z","end":"2021-04-02T11:18:00.000Z"},"country":"United Kingdom","OPM":14,"Total_sales_vol":1231.9299947023392,"rate_of_return":0.05128205128205128}
{"window":{"start":"2021-03-29T00:01:00.000Z","end":"2021-03-29T00:02:00.000Z"},"country":"Malta","OPM":1,"Total_sales_vol":19.799999237060547,"rate_of_return":0.0}
{"window":{"start":"2021-03-27T10:15:00.000Z","end":"2021-03-27T10:16:00.000Z"},"country":"Australia","OPM":1,"Total_sales_vol":53.959999084472656,"rate_of_return":0.0}
{"window":{"start":"2021-03-31T13:45:00.000Z","end":"2021-03-31T13:46:00.000Z"},"country":"United Kingdom","OPM":10,"Total_sales_vol":836.1199690103531,"rate_of_return":0.0625}
{"window":{"start":"2021-03-30T03:18:00.000Z","end":"2021-03-30T03:19:00.000Z"},"country":"Switzerland","OPM":1,"Total_sales_vol":531.0000126361847,"rate_of_return":0.0}
{"window":{"start":"2021-03-31T21:16:00.000Z","end":"2021-03-31T21:17:00.000Z"},"country":"Germany","OPM":1,"Total_sales_vol":50.50999814271927,"rate_of_return":0.0}
{"window":{"start":"2021-03-27T16:49:00.000Z","end":"2021-03-27T16:50:00.000Z"},"country":"United Kingdom","OPM":7,"Total_sales_vol":341.60999751091003,"rate_of_return":0.0}
{"window":{"start":"2021-04-01T23:37:00.000Z","end":"2021-04-01T23:38:00.000Z"},"country":"Hong Kong","OPM":1,"Total_sales_vol":485.27999901771545,"rate_of_return":0.0}
{"window":{"start":"2021-03-27T14:02:00.000Z","end":"2021-03-27T14:03:00.000Z"},"country":"Spain","OPM":1,"Total_sales_vol":25.96000099182129,"rate_of_return":0.0}
{"window":{"start":"2021-03-31T07:43:00.000Z","end":"2021-03-31T07:44:00.000Z"},"country":"Germany","OPM":1,"Total_sales_vol":64.72999854385853,"rate_of_return":0.0}
{"window":{"start":"2021-03-29T19:35:00.000Z","end":"2021-03-29T19:36:00.000Z"},"country":"Germany","OPM":1,"Total_sales_vol":22.22000002861023,"rate_of_return":0.0}
{"window":{"start":"2021-04-02T00:12:00.000Z","end":"2021-04-02T00:13:00.000Z"},"country":"EIRE","OPM":1,"Total_sales_vol":20.400001525878906,"rate_of_return":0.0}
{"window":{"start":"2021-03-26T08:19:00.000Z","end":"2021-03-26T08:20:00.000Z"},"country":"United Kingdom","OPM":7,"Total_sales_vol":902.4299997091293,"rate_of_return":0.0}
{"window":{"start":"2021-03-27T21:49:00.000Z","end":"2021-03-27T21:50:00.000Z"},"country":"United Kingdom","OPM":7,"Total_sales_vol":1703.1700522899628,"rate_of_return":0.0}
{"window":{"start":"2021-03-28T04:27:00.000Z","end":"2021-03-28T04:28:00.000Z"},"country":"United Kingdom","OPM":8,"Total_sales_vol":800.3400177359581,"rate_of_return":0.11904761904761904}
{"window":{"start":"2021-03-28T16:41:00.000Z","end":"2021-03-28T16:42:00.000Z"},"country":"United Kingdom","OPM":11,"Total_sales_vol":632.169998049736,"rate_of_return":0.08333333333333333}
{"window":{"start":"2021-03-31T05:49:00.000Z","end":"2021-03-31T05:50:00.000Z"},"country":"United Kingdom","OPM":4,"Total_sales_vol":127.46999850869179,"rate_of_return":0.0}
{"window":{"start":"2021-03-26T23:48:00.000Z","end":"2021-03-26T23:49:00.000Z"},"country":"United Kingdom","OPM":4,"Total_sales_vol":156.19999986886978,"rate_of_return":0.0}
{"window":{"start":"2021-03-26T15:02:00.000Z","end":"2021-03-26T15:03:00.000Z"},"country":"United Kingdom","OPM":15,"Total_sales_vol":750.6300005316734,"rate_of_return":0.1346153846153846}
{"window":{"start":"2021-03-28T18:01:00.000Z","end":"2021-03-28T18:02:00.000Z"},"country":"France","OPM":1,"Total_sales_vol":128.48999792337418,"rate_of_return":0.0}
{"window":{"start":"2021-03-29T05:58:00.000Z","end":"2021-03-29T05:59:00.000Z"},"country":"United Kingdom","OPM":5,"Total_sales_vol":322.4799967110157,"rate_of_return":0.0}
{"window":{"start":"2021-03-27T18:26:00.000Z","end":"2021-03-27T18:27:00.000Z"},"country":"United Kingdom","OPM":20,"Total_sales_vol":971.8499929308891,"rate_of_return":0.0}
{"window":{"start":"2021-04-01T08:25:00.000Z","end":"2021-04-01T08:26:00.000Z"},"country":"United Kingdom","OPM":10,"Total_sales_vol":748.4099992215633,"rate_of_return":0.0}
{"window":{"start":"2021-03-27T23:39:00.000Z","end":"2021-03-27T23:40:00.000Z"},"country":"Australia","OPM":1,"Total_sales_vol":4.980000019073486,"rate_of_return":0.0}
{"window":{"start":"2021-03-29T02:23:00.000Z","end":"2021-03-29T02:24:00.000Z"},"country":"United Kingdom","OPM":7,"Total_sales_vol":-1190.5800073742867,"rate_of_return":0.15384615384615385}
{"window":{"start":"2021-03-27T06:16:00.000Z","end":"2021-03-27T06:17:00.000Z"},"country":"France","OPM":1,"Total_sales_vol":87.35000228881836,"rate_of_return":0.0}
{"window":{"start":"2021-03-27T00:26:00.000Z","end":"2021-03-27T00:27:00.000Z"},"country":"France","OPM":1,"Total_sales_vol":78.6299991607666,"rate_of_return":0.0}
{"window":{"start":"2021-03-29T16:42:00.000Z","end":"2021-03-29T16:43:00.000Z"},"country":"France","OPM":1,"Total_sales_vol":5.100000381469727,"rate_of_return":0.0}
{"window":{"start":"2021-03-31T18:36:00.000Z","end":"2021-03-31T18:37:00.000Z"},"country":"France","OPM":1,"Total_sales_vol":83.44999849796295,"rate_of_return":0.0}
{"window":{"start":"2021-04-01T04:25:00.000Z","end":"2021-04-01T04:26:00.000Z"},"country":"France","OPM":1,"Total_sales_vol":15.940000534057617,"rate_of_return":0.0}
{"window":{"start":"2021-04-02T13:26:00.000Z","end":"2021-04-02T13:27:00.000Z"},"country":"United Kingdom","OPM":11,"Total_sales_vol":274.31000021100044,"rate_of_return":0.16}
{"window":{"start":"2021-03-27T13:00:00.000Z","end":"2021-03-27T13:01:00.000Z"},"country":"United Kingdom","OPM":18,"Total_sales_vol":1897.4300421476364,"rate_of_return":0.09333333333333334}
{"window":{"start":"2021-03-29T06:47:00.000Z","end":"2021-03-29T06:48:00.000Z"},"country":"United Kingdom","OPM":15,"Total_sales_vol":616.4899972677231,"rate_of_return":0.0}
{"window":{"start":"2021-04-03T08:10:00.000Z","end":"2021-04-03T08:11:00.000Z"},"country":"Belgium","OPM":1,"Total_sales_vol":70.46000075340271,"rate_of_return":0.0}
{"window":{"start":"2021-04-02T05:27:00.000Z","end":"2021-04-02T05:28:00.000Z"},"country":"United Kingdom","OPM":13,"Total_sales_vol":1486.2300010025501,"rate_of_return":0.0}
{"window":{"start":"2021-03-27T11:48:00.000Z","end":"2021-03-27T11:49:00.000Z"},"country":"France","OPM":1,"Total_sales_vol":72.92999935150146,"rate_of_return":0.0}
{"window":{"start":"2021-03-29T01:04:00.000Z","end":"2021-03-29T01:05:00.000Z"},"country":"Unspecified","OPM":1,"Total_sales_vol":14.90999984741211,"rate_of_return":0.0}
{"window":{"start":"2021-03-27T19:40:00.000Z","end":"2021-03-27T19:41:00.000Z"},"country":"Australia","OPM":1,"Total_sales_vol":-82.26000022888184,"rate_of_return":1.0}
{"window":{"start":"2021-03-28T07:19:00.000Z","end":"2021-03-28T07:20:00.000Z"},"country":"United Kingdom","OPM":11,"Total_sales_vol":2388.640010714531,"rate_of_return":0.0}
{"window":{"start":"2021-03-26T19:53:00.000Z","end":"2021-03-26T19:54:00.000Z"},"country":"Germany","OPM":1,"Total_sales_vol":121.92999601364136,"rate_of_return":0.0}
{"window":{"start":"2021-03-28T23:37:00.000Z","end":"2021-03-28T23:38:00.000Z"},"country":"United Kingdom","OPM":4,"Total_sales_vol":114.5300030708313,"rate_of_return":0.0}
{"window":{"start":"2021-04-01T18:11:00.000Z","end":"2021-04-01T18:12:00.000Z"},"country":"United Kingdom","OPM":1,"Total_sales_vol":98.92999935150146,"rate_of_return":0.0}
{"window":{"start":"2021-03-27T19:04:00.000Z","end":"2021-03-27T19:05:00.000Z"},"country":"United Kingdom","OPM":15,"Total_sales_vol":1148.469994366169,"rate_of_return":0.0}
{"window":{"start":"2021-03-29T07:08:00.000Z","end":"2021-03-29T07:09:00.000Z"},"country":"Portugal","OPM":1,"Total_sales_vol":35.19999885559082,"rate_of_return":0.0}
{"window":{"start":"2021-03-31T12:49:00.000Z","end":"2021-03-31T12:50:00.000Z"},"country":"United Kingdom","OPM":5,"Total_sales_vol":182.78999668359756,"rate_of_return":0.0625}
{"window":{"start":"2021-04-01T05:51:00.000Z","end":"2021-04-01T05:52:00.000Z"},"country":"France","OPM":2,"Total_sales_vol":287.13999605178833,"rate_of_return":0.0}
{"window":{"start":"2021-03-26T13:05:00.000Z","end":"2021-03-26T13:06:00.000Z"},"country":"United Kingdom","OPM":6,"Total_sales_vol":439.52000629901886,"rate_of_return":0.0}
{"window":{"start":"2021-03-27T23:55:00.000Z","end":"2021-03-27T23:56:00.000Z"},"country":"Netherlands","OPM":1,"Total_sales_vol":42.83999991416931,"rate_of_return":0.0}
{"window":{"start":"2021-03-27T13:23:00.000Z","end":"2021-03-27T13:24:00.000Z"},"country":"United Kingdom","OPM":10,"Total_sales_vol":212.81001117825508,"rate_of_return":0.13333333333333333}
{"window":{"start":"2021-03-26T04:24:00.000Z","end":"2021-03-26T04:25:00.000Z"},"country":"United Kingdom","OPM":9,"Total_sales_vol":480.5400007367134,"rate_of_return":0.0}
{"window":{"start":"2021-04-02T20:43:00.000Z","end":"2021-04-02T20:44:00.000Z"},"country":"United Kingdom","OPM":5,"Total_sales_vol":385.96000146865845,"rate_of_return":0.0}
{"window":{"start":"2021-03-28T16:39:00.000Z","end":"2021-03-28T16:40:00.000Z"},"country":"Germany","OPM":1,"Total_sales_vol":121.31000518798828,"rate_of_return":0.0}
{"window":{"start":"2021-03-27T07:33:00.000Z","end":"2021-03-27T07:34:00.000Z"},"country":"United Kingdom","OPM":9,"Total_sales_vol":446.8399964570999,"rate_of_return":0.0}
{"window":{"start":"2021-03-30T13:33:00.000Z","end":"2021-03-30T13:34:00.000Z"},"country":"United Kingdom","OPM":12,"Total_sales_vol":337.7299964427948,"rate_of_return":0.0}
{"window":{"start":"2021-03-31T21:30:00.000Z","end":"2021-03-31T21:31:00.000Z"},"country":"United Kingdom","OPM":10,"Total_sales_vol":297.0099919438362,"rate_of_return":0.16666666666666666}
{"window":{"start":"2021-03-28T15:47:00.000Z","end":"2021-03-28T15:48:00.000Z"},"country":"Finland","OPM":1,"Total_sales_vol":81.36000084877014,"rate_of_return":0.0}
{"window":{"start":"2021-03-30T03:56:00.000Z","end":"2021-03-30T03:57:00.000Z"},"country":"United Kingdom","OPM":8,"Total_sales_vol":803.6099954843521,"rate_of_return":0.0}
{"window":{"start":"2021-03-26T22:22:00.000Z","end":"2021-03-26T22:23:00.000Z"},"country":"France","OPM":1,"Total_sales_vol":40.80000150203705,"rate_of_return":0.0}
{"window":{"start":"2021-03-27T12:10:00.000Z","end":"2021-03-27T12:11:00.000Z"},"country":"United Kingdom","OPM":7,"Total_sales_vol":510.4600056409836,"rate_of_return":0.0}
{"window":{"start":"2021-03-27T10:20:00.000Z","end":"2021-03-27T10:21:00.000Z"},"country":"United Kingdom","OPM":16,"Total_sales_vol":2068.650001525879,"rate_of_return":0.0}
{"window":{"start":"2021-03-29T07:41:00.000Z","end":"2021-03-29T07:42:00.000Z"},"country":"United Kingdom","OPM":6,"Total_sales_vol":246.68000161647797,"rate_of_return":0.0}
{"window":{"start":"2021-03-31T10:09:00.000Z","end":"2021-03-31T10:10:00.000Z"},"country":"Israel","OPM":1,"Total_sales_vol":6.599999785423279,"rate_of_return":0.0}
{"window":{"start":"2021-03-28T05:42:00.000Z","end":"2021-03-28T05:43:00.000Z"},"country":"United Kingdom","OPM":9,"Total_sales_vol":702.2699898481369,"rate_of_return":0.0}
{"window":{"start":"2021-03-29T18:38:00.000Z","end":"2021-03-29T18:39:00.000Z"},"country":"United Kingdom","OPM":6,"Total_sales_vol":339.2300008535385,"rate_of_return":0.0}
{"window":{"start":"2021-03-27T07:00:00.000Z","end":"2021-03-27T07:01:00.000Z"},"country":"United Kingdom","OPM":10,"Total_sales_vol":562.0499997138977,"rate_of_return":0.0}
{"window":{"start":"2021-03-29T23:13:00.000Z","end":"2021-03-29T23:14:00.000Z"},"country":"United Kingdom","OPM":12,"Total_sales_vol":786.2599956989288,"rate_of_return":0.0}
{"window":{"start":"2021-03-31T00:35:00.000Z","end":"2021-03-31T00:36:00.000Z"},"country":"Israel","OPM":1,"Total_sales_vol":33.59999895095825,"rate_of_return":0.0}
{"window":{"start":"2021-04-02T18:43:00.000Z","end":"2021-04-02T18:44:00.000Z"},"country":"United Kingdom","OPM":9,"Total_sales_vol":282.83000180125237,"rate_of_return":0.0}
{"window":{"start":"2021-03-28T15:25:00.000Z","end":"2021-03-28T15:26:00.000Z"},"country":"United Kingdom","OPM":13,"Total_sales_vol":1023.9199928045273,"rate_of_return":0.0}
{"window":{"start":"2021-03-28T20:26:00.000Z","end":"2021-03-28T20:27:00.000Z"},"country":"EIRE","OPM":1,"Total_sales_vol":135.30999517440796,"rate_of_return":0.0}
{"window":{"start":"2021-03-29T10:01:00.000Z","end":"2021-03-29T10:02:00.000Z"},"country":"United Kingdom","OPM":9,"Total_sales_vol":703.1299965381622,"rate_of_return":0.0}
{"window":{"start":"2021-04-01T16:14:00.000Z","end":"2021-04-01T16:15:00.000Z"},"country":"United Kingdom","OPM":11,"Total_sales_vol":352.37000024318695,"rate_of_return":0.0}
{"window":{"start":"2021-03-27T11:05:00.000Z","end":"2021-03-27T11:06:00.000Z"},"country":"Norway","OPM":1,"Total_sales_vol":49.560001373291016,"rate_of_return":0.0}
{"window":{"start":"2021-03-29T05:19:00.000Z","end":"2021-03-29T05:20:00.000Z"},"country":"Denmark","OPM":1,"Total_sales_vol":161.0100000500679,"rate_of_return":0.0}
{"window":{"start":"2021-04-01T02:44:00.000Z","end":"2021-04-01T02:45:00.000Z"},"country":"United Kingdom","OPM":12,"Total_sales_vol":838.7100031375885,"rate_of_return":0.1}
{"window":{"start":"2021-04-02T17:32:00.000Z","end":"2021-04-02T17:33:00.000Z"},"country":"EIRE","OPM":1,"Total_sales_vol":14.5,"rate_of_return":0.0}
{"window":{"start":"2021-04-01T22:01:00.000Z","end":"2021-04-01T22:02:00.000Z"},"country":"Cyprus","OPM":1,"Total_sales_vol":1.25,"rate_of_return":0.0}
{"window":{"start":"2021-04-01T07:18:00.000Z","end":"2021-04-01T07:19:00.000Z"},"country":"EIRE","OPM":1,"Total_sales_vol":33.040000915527344,"rate_of_return":0.0}
{"window":{"start":"2021-03-31T23:17:00.000Z","end":"2021-03-31T23:18:00.000Z"},"country":"United Kingdom","OPM":12,"Total_sales_vol":869.7399979531765,"rate_of_return":0.0}
{"window":{"start":"2021-04-03T05:58:00.000Z","end":"2021-04-03T05:59:00.000Z"},"country":"United Kingdom","OPM":15,"Total_sales_vol":1323.4599980711937,"rate_of_return":0.0}
{"window":{"start":"2021-03-31T01:25:00.000Z","end":"2021-03-31T01:26:00.000Z"},"country":"United Kingdom","OPM":10,"Total_sales_vol":510.97000819444656,"rate_of_return":0.0}
{"window":{"start":"2021-03-26T13:46:00.000Z","end":"2021-03-26T13:47:00.000Z"},"country":"EIRE","OPM":1,"Total_sales_vol":9.049999713897705,"rate_of_return":0.0}
{"window":{"start":"2021-03-26T00:58:00.000Z","end":"2021-03-26T00:59:00.000Z"},"country":"Netherlands","OPM":1,"Total_sales_vol":24.78000020980835,"rate_of_return":0.0}
{"window":{"start":"2021-04-02T09:51:00.000Z","end":"2021-04-02T09:52:00.000Z"},"country":"United Kingdom","OPM":11,"Total_sales_vol":295.7599915266037,"rate_of_return":0.14285714285714285}
{"window":{"start":"2021-04-01T06:02:00.000Z","end":"2021-04-01T06:03:00.000Z"},"country":"United Kingdom","OPM":8,"Total_sales_vol":416.63000386953354,"rate_of_return":0.0}
{"window":{"start":"2021-03-29T20:06:00.000Z","end":"2021-03-29T20:07:00.000Z"},"country":"United Kingdom","OPM":8,"Total_sales_vol":262.80999940633774,"rate_of_return":0.0}
{"window":{"start":"2021-03-30T14:28:00.000Z","end":"2021-03-30T14:29:00.000Z"},"country":"United Kingdom","OPM":7,"Total_sales_vol":197.01999723911285,"rate_of_return":0.0625}
{"window":{"start":"2021-03-31T03:53:00.000Z","end":"2021-03-31T03:54:00.000Z"},"country":"United Kingdom","OPM":5,"Total_sales_vol":338.13000547885895,"rate_of_return":0.2631578947368421}
{"window":{"start":"2021-03-31T03:53:00.000Z","end":"2021-03-31T03:54:00.000Z"},"country":"Germany","OPM":1,"Total_sales_vol":3.75,"rate_of_return":0.0}
